pyupgrade_directory.py
pyupgrade_directory-0.0.0.dist-info/METADATA
pyupgrade_directory-0.0.0.dist-info/WHEEL
pyupgrade_directory-0.0.0.dist-info/entry_points.txt
pyupgrade_directory-0.0.0.dist-info/top_level.txt
pyupgrade_directory-0.0.0.dist-info/RECORD
